<?xml version="1.0" encoding="utf-8"?>
<resources>
    <!-- Change log of the Android App v3.8.0. Keep the dash character (-) and line breaks to keep the list format. -->
    <string name="andoid_change_log">- Bày tỏ cảm xúc bằng emoji cho tin nhắn.\n- Cải thiện chất lượng gọi thoại và video.\n- Cải thiện Đăng Tải Camêra.\n- Cải thiện hỗ trợ cho dịnh dạng tệp video MKV.\n- Cải thiện chức năng tìm kiếm.\n- Khắc phục các lỗi nhỏ khác.</string>
    <!-- Change log of the Android App v3.8.1. Keep the dash character (-) and line breaks to keep the list format. -->
    <string name="andoid_change_log_v3_8_1">- Thêm widget mới hiển thị truyền tải.\n- Cải thiện truyền tải và giao diện sử dụng.\n- Thêm chế độ “Không Làm Phiền”.\n- Cải thiện hiển thị các thông báo.\n- Cải thiện cách thức thanh toán qua CH Google Play (Google Play Billing Library mới).\n- Sửa chữa các lỗi nhỏ khác.</string>
    <!-- Change log of the Android App v3.8.2. Keep the dash character (-) and line breaks to keep the list format. -->
    <string name="andoid_change_log_v3_8_2">- Thêm tùy chọn để giữ cuộc gọi.\n- Cải thiện giao diện cuộc gọi và thông báo.\n- Thêm mức giới hạn về số lượng bày tỏ cảm xúc cho tin nhắn.\n- Thêm dịch vụ thông báo công khai về bất kỳ thông báo quan trọng nào từ MEGA.\n- Thêm tùy chọn GIPHY vào thanh cộng cụ chát.\n- Cải thiện phát hình động GIF trong phần chát.</string>
    <!-- Change log of the Android App v3.8.3. Keep the dash character (-) and line breaks to keep the list format. -->
    <string name="android_change_log_v3_8_3">- Thiết kế lại trang thiết đặt.\n- Cải thiện thời gian tải sau khi xoay màn hình trong lúc truyền phát âm thanh / video.\n- Cải thiện và sửa chữa một số lỗi nhỏ khác</string>
    <!-- Change log of the Android App v3.8.4. Keep the dash character (-) and line breaks to keep the list format. -->
    <string name="android_change_log_v3_8_4">- Thêm chức năng hồi phục phiên truyền tải.\n- Hiện thị giá cả với đồng tiền tệ của địa phương khi nâng cấp tài khoản.\n- Cải thiện và sửa chữa một số lỗi nhỏ khác.</string>
    <!-- Change log of the Android App v3.8.5. Keep the dash character (-) and line breaks to keep the list format. -->
    <string name="android_change_log_v3_8_5">- Thêm mục Trang Chủ.\n- Thêm lựa chọn để đánh dấu ưa thích cho tệp tin và thư mục.\n- Thêm khả năng dán nhãn màu sắc cho tệp tin và thư mục.\n- Vài cải thiện và sửa chữa lỗi nhỏ khác.</string>
    <!-- Change log of the Android App v4.0.0. Keep the dash character (-) and line breaks to keep the list format. -->
    <string name="android_change_log_v4_0_0">- Thêm cài đặt cookie mới.\n- Cải thiện giao diện khi lấy đường liên kết.\n- Cải thiện trang hiển thị các truyền tải.\n- Cải thiện thông báo về dịch vụ chung và quan trọng từ MEGA.\n- Một số cải thiện sửa chữa lỗi nhỏ khác.</string>
    <!-- Change log of the Android App v4.0.1. Keep the dash character (-) and line breaks to keep the list format. -->
    <string name="android_change_log_v4_0_1">- Thêm vào trang chính một khung chứa các chức năng nổi bật.\n- Thêm vào thiết đặt để chọn tự động việc dọn dẹp lịch sử cuộc trò chuyện.\n- Cải thiện và sửa chữa một số lỗi nhỏ khác.</string>
    <!-- Change log of the Android App v4.0.2. Keep the dash character (-) and line breaks to keep the list format. -->
    <string name="android_change_log_v4_0_2">- Thêm chức&#160;năng quét tài&#160;liệu mới.\n- Cải&#160;thiện và sửa&#160;chữa một&#160;số lỗi nhỏ.</string>
    <!-- Change log of the Android App v4.1.0. Keep the dash character (-) and line breaks to keep the list format. -->
    <string name="android_change_log_v4_1_0">- Thêm giao diện nền tối.\n- Sửa lỗi và cải thiện hiệu xuất.</string>
    <!-- Change log of the Android App v4.1.1. Keep the dash character (-) and line breaks to keep the list format. -->
    <string name="android_change_log_v4_1_1">- Trình phát âm thanh mới có khả năng duy trì phát nhạc trong nền sử dụng danh sách tự động với các tệp âm thanh được lưu trong MEGA.\n- Trình phát video mới có khả năng phát danh sách tự động các tệp video được lưu trong MEGA.\n- Thùng Rác hiện đã có trong khu điều hướng.\n- Sửa lỗi và cải thiện hiệu xuất.</string>
    <!-- Change log of the Android App v4.1.2. Keep the dash character (-) and line breaks to keep the list format. -->
    <string name="android_change_log_v4_1_2">- Tùy chọn đặt hết giờ cho khóa mã số và cập&#160;nhật giao&#160;diện.\n- Sửa lỗi hỏng và cải&#160;thiện hiệu&#160;xuất.</string>
    <!-- Change log of the Android App v4.1.3. Keep the dash character (-) and line breaks to keep the list format. -->
    <string name="android_change_log_v4_1_3">- Thêm bộ soạn thảo văn bản để giúp chỉnh sửa nội dung của các tệp tài liệu.\n- Sửa lỗi và cải thiện hiệu xuất.</string>
    <!-- Change log of the Android App v4.1.4. Keep the dash character (-) and line breaks to keep the list format. -->
    <string name="android_change_log_v4_1_4">- Cập nhật giao diện cho xác&#160;thực 2&#160;yếu&#160;tố.\n- Sửa lỗi và cải thiện hiệu xuất.</string>
    <!-- Change log of the Android App v4.1.5. Keep the dash character (-) and line breaks to keep the list format. -->
    <string name="android_change_log_v4_1_5">- Sửa lỗi và cải thiện hiệu xuất.</string>
    <!-- Change log of the Android App v4.1.6. Keep the dash character (-) and line breaks to keep the list format. -->
    <string name="android_change_log_v4_1_6">- Giờ đây bạn có thể lưu hình và videos từ MEGA vào thẳng thư viện hình ảnh trong máy.\n- Sửa lỗi và cải thiện hiệu xuất.</string>
    <!-- Change log of the Android App v4.2.0. Keep the dash character (-) and line breaks to keep the list format. -->
    <string name="android_change_log_v4_2_0">- Giao diện mới cho chức năng Đăng Tải Camêra giúp tìm kiếm và chia sẻ nội dung tốt hơn. Sắp xếp và tra tìm hình ảnh và videos theo ngày, tháng hoặc năm.\n- Cho phép nhảy 15 giây tiến hoặc lùi khi sử dụng điều khiển trình phát âm thanh.\n- Sửa lỗi và cải thiện hiệu xuất.</string>
    <!-- Change log of the Android App v4.2.1. Keep the dash character (-) and line breaks to keep the list format. -->
    <string name="android_change_log_v4_2_1">- Sửa lỗi và cải thiện hiệu xuất.</string>
    <!-- Change log of the Android App v4.2.2. Keep the dash character (-) and line breaks to keep the list format. -->
    <string name="android_change_log_v4_2_2">- Giờ đây đã có nút bấm để tua tiến hoặc lùi 15 giây trong giao diện phát video.\n- Việc xử lý và chỉnh sửa các tệp tin văn bản có kích thước lớn giờ có hiệu quả hơn, lên tới 20 MB.\n- Sửa lỗi và cải thiện hiệu xuất.</string>
    <!-- Change log of the Android App v4.3. Keep the dash character (-) and line breaks to keep the list format. -->
    <string name="android_change_log_v4_3">- Giờ đây bạn có thể tạo và chia sẻ nhiều đường liên kết cùng một lúc.\n- Giao diện mới cho Sổ Liên Lạc và trang Tài&#160;Khoản của Tôi.\n- Nâng cao khả năng hỗ trợ cho các thiết bị Android 11.\n- Sửa lỗi và cải thiện hiệu xuất.</string>
    <!-- Change log of the Android App v5.0. Keep the dash character (-) and line breaks to keep the list format. -->
    <string name="android_change_log_v5_0">- Giao diện gọi điện của MEGA chat được làm mới.\n- Người dùng hiện có thể tham gia cuộc gọi MEGAchát thông qua đường liên kết với tư cách khách hoặc với tên tài khoản chính thức.\n- Tăng cường số lượng người tham gia cho phép trong cuộc gọi.\n- Sửa lỗi và cải thiện hiệu xuất.</string>
    <!-- Change log of the Android App v5.1. Keep the dash character (-) and line breaks to keep the list format. -->
    <string name="android_change_log_v5_1">- Sửa lỗi và cải thiện hiệu xuất.</string>
    <!-- Change log of the Android App v5.1.1. Keep the dash character (-) and line breaks to keep the list format. -->
    <string name="android_change_log_v5_1_1">- Sửa lỗi và cải thiện hiệu xuất.</string>
    <!-- Change log of the Android App v5.2. Keep the dash character (-) and line breaks to keep the list format. -->
    <string name="android_change_log_v5_2">- Giờ đây bạn có thể đặt chất lượng video lưu vào Đăng Tải Camêra và khi gửi kèm vào Chát. \n- Sửa lỗi và cải thiện hiệu xuất.</string>
    <!-- Change log of the Android App v5.3. Keep the dash character (-) and line breaks to keep the list format. -->
    <string name="android_change_log_v5_3">- Ẩn đi lịch sử hoạt động hiển thị ở mục Gần Đây bằng cách vào Thiết Đặt &gt; Giao Diện Sử Dụng &gt; Ẩn hoạt động gần đây\n- Có lựa chọn mới để hiện trang khởi đầu mỗi khi mở app\n- Sửa lỗi và cải thiện hiệu xuất.</string>
    <!-- Change log of the Android App v5.4. Keep the dash character (-) and line breaks to keep the list format. -->
    <string name="android_change_log_v5_4">- Giờ đây bạn có thể mở khóa MEGA bằng dấu vân tay\n- Giảm tải không gian lưu trữ bằng cách chọn ra chất lượng video muốn tải lên trong Thiết Đặt Đăng Tải Camêra\n- Thu, phóng hình được thêm vào chế độ xem thư viện\n- Sửa lỗi và cải thiện hiệu xuất.</string>
    <!-- Change log of the Android App v5.5. Keep the dash character (-) and line breaks to keep the list format. -->
    <string name="android_change_log_v5_5">- Sửa lỗi và cải thiện hiệu xuất.</string>
    <!-- Change log of the Android App v6.0. Keep the dash character (-) and line breaks to keep the list format. -->
    <string name="android_change_log_v6_0">- Sửa lỗi và cải thiện hiệu xuất.</string>
    <!-- Change log of the Android App v6.1. Keep the dash character (-) and line breaks to keep the list format. -->
    <string name="android_change_log_v6_1">- Chế độ xem thư viện hình ảnh giờ có thể truy cập ở dưới phần tên của thư mục. Bạn có thể chuyển đổi chế độ xem theo kiểu danh sách, ảnh nhỏ, và thư viện\n- Cho phép xem trước hình ảnh với độ phân giải toàn màn hình\n- Mang tùy chọn “Mở liên kết” quay trở lại menu\n- Sửa lỗi và cải thiện hiệu xuất</string>
    <!-- Change log of the Android App v6.2. Keep the dash character (-) and line breaks to keep the list format. -->
    <string name="android_change_log_v6_2">- Tính năng ’thư mục tải lên’ mới cho phép lựa chọn tải lên trọn bộ cả một thư mục hoặc hơn\n- Thêm tùy chọn để xắp xếp lại danh sách phát âm thanh và video\n- Sửa lỗi và cải thiện hiệu xuất</string>
    <!-- Change log of the Android App v6.3. Keep the dash character (-) and line breaks to keep the list format. -->
    <string name="android_change_log_v6_3">- Cải thiện trải nghiệm người dùng quản lý phương thức thanh toán cho gói đăng ký dịch vụ tài khoản Pro\n- Sửa lỗi và cải thiện hiệu xuất</string>
    <!-- Change log of the Android App v6.4. Keep the dash character (-) and line breaks to keep the list format. -->
    <string name="android_change_log_v6_4">- Ngừng hỗ trợ phiên bản Android 5.x \n- Tăng cường chất lượng hỗ trợ Android 12\n- Cải thiện trải nghiệm sử dụng khách hàng trong quá trình thanh toán thay đổi tài khoản hạng Pro\n- Sửa lỗi và cải thiện hiệu xuất</string>
    <!-- Change log of the Android App v6.5. Keep the dash character (-) and line breaks to keep the list format. -->
    <string name="android_change_log_v6_5">- Giờ đây bạn có thể xem album ưa thích của mình trong phần Ảnh\n- Biểu hiện có cuộc gọi đang diễn ra ở phần Trang Chủ\n- Cải thiện trải nghiệm khách hàng về vấn đề thanh toán\n- Cải thiện trải nghiệm sử dụng khi xóa bỏ tài khoản còn gói đăng ký dịch vụ có hoạt động\n- Sửa lỗi và cải thiện hiệu xuất</string>
    <!-- Change log of the Android App v6.6. Keep the dash character (-) and line breaks to keep the list format. -->
    <string name="android_change_log_v6_6">- Giờ đây bạn có thể xem các mục ưa thích của mình trong phần Trang Chủ\n- Sửa lỗi và cải thiện hiệu xuất</string>
    <!-- Change log of the Android App v6.7. Keep the dash character (-) and line breaks to keep the list format. -->
    <string name="android_change_log_v6_7">- Tìm tên liên lạc trong Chát giờ đây trở nên dễ dàng hơn bao giờ hết, điền tên, e-mail hoặc biệt danh muốn tìm\n- Sửa lỗi và cải thiện hiệu xuất</string>
    <!-- Change log of the Android App v6.8. Keep the dash character (-) and line breaks to keep the list format. -->
    <string name="android_change_log_v6_8">- Sửa lỗi và cải thiện hiệu xuất</string>
    <!-- Change log of the Android App v6.9. Keep the dash character (-) and line breaks to keep the list format. -->
    <string name="android_change_log_v6_9">- Sửa lỗi và cải thiện hiệu xuất.</string>
    <!-- Change log of the Android App v6.10. Keep the dash character (-) and line breaks to keep the list format. -->
    <string name="android_change_log_v6_10">- Giờ đây bạn có thể đặt chất lượng hình ảnh khi gửi kèm vào chát sử dụng dữ liệu mạng di động.\n- Sửa lỗi và cải thiện hiệu xuất.</string>
    <!-- Change log of the Android App v6.10.1. Keep the dash character (-) and line breaks to keep the list format. -->
    <string name="android_change_log_v6_10_1">- Sửa lỗi và cải thiện hiệu xuất.</string>
    <!-- Change log of the Android App v6.11. Keep the dash character (-) and line breaks to keep the list format. -->
    <string name="android_change_log_v6_11">- Các mục được đánh dấu ưa thích của bạn sẽ được tìm dễ hơn với thẻ Ưa Thích được đem ra màn hình trang chủ.\n- Tất cả hình ảnh có trong ổ mây của bạn giờ đây sẽ hiện trong phần Ảnh.\n- Bạn có thể mở khóa truy cập mã PIN và khóa vân tay bằng cách sử dụng mật khẩu.\n- Cải tiến quá trình quản lý các mục bị trùng lặp khi tải lên, sao chép hoặc di chuyển tệp tin bên trong ứng dụng.\n- Quản lý truyền tải và tốc độ tải lên / xuống được chắc chắn hơn .\n- Sửa lỗi và cải thiện hiệu xuất.</string>
    <!-- Change log of the Android App v6.12. Keep the dash character (-) and line breaks to keep the list format. Note: 'Settings'(key:action_settings), 'Help'(key: settings_help) and 'Report issue'(key:settings_help_report_issue) are UI elements-->
    <string name="android_change_log_v6_12">- Cải thiện thanh công cụ chát tăng cường trải nghiệm cuộc trò chuyện.\n- Cho phép gửi báo cáo trong phần Thiết Đặt &gt; Trợ Giúp &gt; Báo cáo lỗi.\n- Sửa lỗi và cải thiện hiệu xuất.</string>
    <!-- Change log of the Android App v6.12.1. Keep the dash character (-) and line breaks to keep the list format. -->
    <string name="android_change_log_v6_12_1">- Sửa lỗi và cải thiện hiệu xuất.</string>
    <!-- Change log of the Android App v6.13. Keep the dash character (-) and line breaks to keep the list format. -->
    <string name="android_change_log_v6_13">- Tùy chọn cho người chủ trì cuộc họp khi muốn chấm dứt cuộc gọi cho tất cả các thành viên.\n- Sửa lỗi và cải thiện hiệu xuất.</string>
    <!-- Change log of the Android App v6.14. Keep the dash character (-) and line breaks to keep the list format. -->
    <string name="android_change_log_v6_14">- Sửa lỗi và cải thiện hiệu xuất</string>
    <!-- Change log of the Android App v6.14.1. Keep the dash character (-) and line breaks to keep the list format. -->
    <string name="android_change_log_v6_14_1">- Sửa lỗi và cải thiện hiệu xuất</string>
    <!-- Change log of the Android App v6.15. Keep the dash character (-) and line breaks to keep the list format. -->
    <string name="android_change_log_v6_15">- Thẻ mới dành riêng cho chát và họp\n- Khả năng mở các tệp tài liệu Microsoft bằng cách sử dụng ứng dụng của Microsoft\n- Sửa lỗi và cải thiện hiệu xuất</string>
    <!-- Change log of the Android App 7.0. Keep the dash character (-) and line breaks to keep the list format. -->
    <string name="android_change_log_v7_0">- Bộ nhớ của thiết bị giờ đây sẽ được sử dụng ít hơn khi app đang hoạt động.\n- Các bản cập nhật cho Android 6 sẽ không còn được cung cấp.\n- Hỗ trợ thêm nhiều loại định dạng ảnh RAW.\n- Sửa lỗi và cải thiện hiệu xuất.</string>
    <!-- Change log of the Android App 7.6. Keep the dash character (-) and line breaks to keep the list format. -->
    <string name="android_change_log_v7_6">- Giờ đây, bạn có thể xem và tham&#160;gia các cuộc&#160;họp đã lên lịch.\n- Bạn sẽ nhận được các thông&#160;báo về cuộc&#160;họp đã lên lịch mà bạn đã được mời tham&#160;dự.\n- Sửa lỗi và cải&#160;thiện hiệu&#160;suất.</string>
    <!-- Change log of Android App 8.0 . Keep the dash character (-) and line breaks to keep the list format. -->
    <string name="android_change_log_v8_0">- Giờ đây bạn có&#160;thể sắp&#160;xếp các hình&#160;ảnh và videos của bạn thành album.\n- Bạn có&#160;thể thêm phụ&#160;đề vào các videos của bạn.\n- Lỗi đã được sửa và hiệu&#160;suất được cải&#160;thiện.</string>
    <!-- Change log of Android App 9.0 . Keep the dash character (-) and line breaks to keep the list format. -->
    <string name="android_change_log_v9_0">- Bạn giờ đây có thể đặt lịch cuộc họp một&#160;lần và định&#160;kỳ.\n- Thêm hỗ&#160;trợ cho Android 14.\n- Thêm hỗ&#160;trợ cho các định&#160;dạng video .mkv và .avi.</string>
    <!-- Change log of Android App 10.0 . Keep the dash character (-) and line breaks to keep the list format. -->
    <string name="android_change_log_v10_0">- Tính&#160;năng chia&#160;sẻ album hiện đã được phát&#160;hành.\n- Sửa lỗi hỏng và cải&#160;thiện hiệu&#160;xuất.</string>
</resources>